{
  "id": "2086655",
  "name": "地图",
  "font_family": "iconfont",
  "css_prefix_text": "icon-",
  "description": "",
  "glyphs": [
    {
      "icon_id": "3868163",
      "name": "电脑",
      "font_class": "diannao",
      "unicode": "e60d",
      "unicode_decimal": 58893
    },
    {
      "icon_id": "4186487",
      "name": "钱",
      "font_class": "qian",
      "unicode": "e62b",
      "unicode_decimal": 58923
    },
    {
      "icon_id": "4482966",
      "name": "胶卷",
      "font_class": "jiaojuan",
      "unicode": "e67d",
      "unicode_decimal": 59005
    },
    {
      "icon_id": "6319183",
      "name": "公厕",
      "font_class": "gongce",
      "unicode": "e676",
      "unicode_decimal": 58998
    },
    {
      "icon_id": "7843634",
      "name": "美食",
      "font_class": "fenzu",
      "unicode": "e61d",
      "unicode_decimal": 58909
    },
    {
      "icon_id": "9841597",
      "name": "购物",
      "font_class": "gouwu",
      "unicode": "e614",
      "unicode_decimal": 58900
    },
    {
      "icon_id": "9842006",
      "name": "停车",
      "font_class": "tingche",
      "unicode": "e621",
      "unicode_decimal": 58913
    },
    {
      "icon_id": "10142561",
      "name": "详情",
      "font_class": "detail",
      "unicode": "e606",
      "unicode_decimal": 58886
    },
    {
      "icon_id": "1350135",
      "name": "定位",
      "font_class": "location",
      "unicode": "e61a",
      "unicode_decimal": 58906
    },
    {
      "icon_id": "1411034",
      "name": "岔口22",
      "font_class": "chakou",
      "unicode": "e620",
      "unicode_decimal": 58912
    },
    {
      "icon_id": "2170916",
      "name": "地图模式",
      "font_class": "ditumoshi",
      "unicode": "e604",
      "unicode_decimal": 58884
    },
    {
      "icon_id": "5037717",
      "name": "下箭头",
      "font_class": "xiajiantou",
      "unicode": "e629",
      "unicode_decimal": 58921
    },
    {
      "icon_id": "5701368",
      "name": "地铁2小",
      "font_class": "ditiexiao",
      "unicode": "e941",
      "unicode_decimal": 59713
    },
    {
      "icon_id": "7055635",
      "name": "日历",
      "font_class": "rili",
      "unicode": "e72a",
      "unicode_decimal": 59178
    },
    {
      "icon_id": "11502406",
      "name": "查价格-壹米滴答",
      "font_class": "chajiage-yimidida",
      "unicode": "e667",
      "unicode_decimal": 58983
    },
    {
      "icon_id": "11641868",
      "name": "叉",
      "font_class": "cha",
      "unicode": "e61c",
      "unicode_decimal": 58908
    },
    {
      "icon_id": "12577309",
      "name": "G03_08合作楼盘_hzlp",
      "font_class": "G_hezuoloupan_hzlp",
      "unicode": "e643",
      "unicode_decimal": 58947
    },
    {
      "icon_id": "16584514",
      "name": "电  话",
      "font_class": "dianhua",
      "unicode": "e76a",
      "unicode_decimal": 59242
    },
    {
      "icon_id": "4511969",
      "name": "减少",
      "font_class": "jianshao",
      "unicode": "e644",
      "unicode_decimal": 58948
    },
    {
      "icon_id": "1302",
      "name": "加",
      "font_class": "jia",
      "unicode": "e600",
      "unicode_decimal": 58880
    },
    {
      "icon_id": "1427",
      "name": "公交",
      "font_class": "gongjiao",
      "unicode": "e601",
      "unicode_decimal": 58881
    },
    {
      "icon_id": "110429",
      "name": "设置",
      "font_class": "shezhi",
      "unicode": "e602",
      "unicode_decimal": 58882
    },
    {
      "icon_id": "637803",
      "name": "向上箭头",
      "font_class": "xiangshangjiantou",
      "unicode": "e62f",
      "unicode_decimal": 58927
    },
    {
      "icon_id": "827618",
      "name": "地图",
      "font_class": "ditu",
      "unicode": "e648",
      "unicode_decimal": 58952
    },
    {
      "icon_id": "2268437",
      "name": "卫星",
      "font_class": "weixing",
      "unicode": "e608",
      "unicode_decimal": 58888
    },
    {
      "icon_id": "3874042",
      "name": "搜索",
      "font_class": "sousuo",
      "unicode": "e636",
      "unicode_decimal": 58934
    },
    {
      "icon_id": "4231889",
      "name": "走路",
      "font_class": "zoulu",
      "unicode": "e60a",
      "unicode_decimal": 58890
    },
    {
      "icon_id": "6775451",
      "name": "骑车",
      "font_class": "yiliaohangyedeICON-",
      "unicode": "e635",
      "unicode_decimal": 58933
    },
    {
      "icon_id": "7791021",
      "name": "汽车",
      "font_class": "qiche",
      "unicode": "e7ef",
      "unicode_decimal": 59375
    },
    {
      "icon_id": "9474543",
      "name": "定位",
      "font_class": "dingwei",
      "unicode": "e619",
      "unicode_decimal": 58905
    },
    {
      "icon_id": "11200352",
      "name": "红绿灯",
      "font_class": "traffic-status",
      "unicode": "e603",
      "unicode_decimal": 58883
    },
    {
      "icon_id": "11372655",
      "name": "地图",
      "font_class": "ditu1",
      "unicode": "e8ad",
      "unicode_decimal": 59565
    },
    {
      "icon_id": "11906577",
      "name": "下载",
      "font_class": "xiazai",
      "unicode": "e6be",
      "unicode_decimal": 59070
    },
    {
      "icon_id": "12686755",
      "name": "加",
      "font_class": "icon-",
      "unicode": "e64c",
      "unicode_decimal": 58956
    },
    {
      "icon_id": "15685592",
      "name": "箭头_上下切换",
      "font_class": "jiantou_shangxiaqiehuan",
      "unicode": "e6eb",
      "unicode_decimal": 59115
    }
  ]
}
